langchain_graph_retriever/__init__.py
langchain_graph_retriever/_conversion.py
langchain_graph_retriever/document_graph.py
langchain_graph_retriever/graph_retriever.py
langchain_graph_retriever/py.typed
langchain_graph_retriever/adapters/__init__.py
langchain_graph_retriever/adapters/astra.py
langchain_graph_retriever/adapters/cassandra.py
langchain_graph_retriever/adapters/chroma.py
langchain_graph_retriever/adapters/in_memory.py
langchain_graph_retriever/adapters/inference.py
langchain_graph_retriever/adapters/langchain.py
langchain_graph_retriever/adapters/open_search.py
langchain_graph_retriever/transformers/__init__.py
langchain_graph_retriever/transformers/gliner.py
langchain_graph_retriever/transformers/html.py
langchain_graph_retriever/transformers/keybert.py
langchain_graph_retriever/transformers/parent.py
langchain_graph_retriever/transformers/shredding.py
langchain_graph_retriever/transformers/spacy.py
langchain_graph_retriever-0.8.0.dist-info/METADATA
langchain_graph_retriever-0.8.0.dist-info/WHEEL
langchain_graph_retriever-0.8.0.dist-info/licenses/LICENSE
langchain_graph_retriever-0.8.0.dist-info/RECORD
